{
    "avg": {
        "wmc": 7.57,
        "ccn": 4.27,
        "bugs": 0.13,
        "kanDefect": 0.44,
        "relativeSystemComplexity": 106.84,
        "relativeDataComplexity": 1.25,
        "relativeStructuralComplexity": 105.59,
        "volume": 386.5,
        "commentWeight": 18.81,
        "intelligentContent": 48.37,
        "lcom": 1.35,
        "instability": 0.42,
        "afferentCoupling": 0.86,
        "efferentCoupling": 1.73,
        "difficulty": 8.83,
        "mi": 69.92,
        "distance": 0.23,
        "incomingCDep": 1.38,
        "incomingPDep": 1,
        "outgoingCDep": 3.38,
        "outgoingPDep": 2.13,
        "classesPerPackage": 4.63
    },
    "sum": {
        "loc": 2014,
        "cloc": 239,
        "lloc": 1775,
        "nbMethods": 159,
        "nbClasses": 37,
        "nbInterfaces": 0,
        "nbPackages": 8,
        "violations": {
            "total": 7,
            "information": 0,
            "warning": 6,
            "error": 1,
            "critical": 0
        }
    }
}